{
  "uid": {
    "__TYPE__": "UIDContent",
    "value": "although"
  },
  "title": {
    "__TYPE__": "StructuredTextContent",
    "value": [
      {
        "type": "heading1",
        "content": {
          "text": "Laugh"
        }
      }
    ]
  },
  "menuLinks": {
    "__TYPE__": "GroupContentType",
    "value": [
      {
        "__TYPE__": "GroupItemContent",
        "value": [
          [
            "link",
            {
              "__TYPE__": "LinkContent",
              "value": {
                "__TYPE__": "ExternalLink",
                "url": "https://slicemachine.dev"
              }
            }
          ],
          [
            "label",
            {
              "__TYPE__": "StructuredTextContent",
              "value": [
                {
                  "type": "paragraph",
                  "content": {
                    "text": "Duis aliquip nostrud ullamco id sint esse adipisicing deserunt ex velit reprehenderit. Ut do laboris officia officia. Pariatur consequat magna et est anim dolor id et deserunt reprehenderit aliqua elit consequat."
                  }
                }
              ]
            }
          ]
        ]
      }
    ]
  },
  "logo": {
    "__TYPE__": "ImageContent",
    "origin": {
      "id": "main",
      "url": "https://images.unsplash.com/photo-1515378960530-7c0da6231fb1",
      "width": 5616,
      "height": 3744
    },
    "url": "https://images.unsplash.com/photo-1515378960530-7c0da6231fb1",
    "width": 5616,
    "height": 3744,
    "edit": {
      "zoom": 1,
      "crop": {
        "x": 0,
        "y": 0
      },
      "background": "transparent"
    },
    "thumbnails": {}
  },
  "buttonLabel": {
    "__TYPE__": "StructuredTextContent",
    "value": [
      {
        "type": "paragraph",
        "content": {
          "text": "Duis commodo sit occaecat irure nostrud ex nisi irure proident incididunt culpa deserunt consequat ut exercitation."
        }
      }
    ]
  },
  "buttonLink": {
    "__TYPE__": "LinkContent",
    "value": {
      "__TYPE__": "ExternalLink",
      "url": "https://slicemachine.dev"
    }
  },
  "socialInstagram": {
    "__TYPE__": "LinkContent",
    "value": {
      "__TYPE__": "ExternalLink",
      "url": "https://slicemachine.dev"
    }
  },
  "socialFacebook": {
    "__TYPE__": "LinkContent",
    "value": {
      "__TYPE__": "ExternalLink",
      "url": "http://twitter.com"
    }
  },
  "linkTerms": {
    "__TYPE__": "LinkContent",
    "value": {
      "__TYPE__": "ExternalLink",
      "url": "https://slicemachine.dev"
    }
  },
  "linkPrivacy": {
    "__TYPE__": "LinkContent",
    "value": {
      "__TYPE__": "ExternalLink",
      "url": "http://google.com"
    }
  },
  "linkTermsLabel": {
    "__TYPE__": "StructuredTextContent",
    "value": [
      {
        "type": "paragraph",
        "content": {
          "text": "Aliquip ex officia eu sit et anim mollit dolor ut ut duis ad ullamco irure ullamco. Minim irure sunt reprehenderit esse incididunt laborum consectetur cillum sit eiusmod ex qui. Incididunt id occaecat non nisi commodo deserunt commodo labore velit commodo eiusmod."
        }
      }
    ]
  },
  "linkPrivacyLabel": {
    "__TYPE__": "StructuredTextContent",
    "value": [
      {
        "type": "paragraph",
        "content": {
          "text": "Sunt dolore ipsum magna."
        }
      }
    ]
  }
}